llama_index/py.typed
llama_index/vector_stores/lindorm/__init__.py
llama_index/vector_stores/lindorm/base.py
llama_index_vector_stores_lindorm-0.4.1.dist-info/METADATA
llama_index_vector_stores_lindorm-0.4.1.dist-info/WHEEL
llama_index_vector_stores_lindorm-0.4.1.dist-info/licenses/LICENSE
llama_index_vector_stores_lindorm-0.4.1.dist-info/RECORD
